CHANGELOG.md
LICENSE
MANIFEST.in
README.md
setup.cfg
setup.py
pip_services3_prometheus/__init__.py
pip_services3_prometheus.egg-info/PKG-INFO
pip_services3_prometheus.egg-info/SOURCES.txt
pip_services3_prometheus.egg-info/dependency_links.txt
pip_services3_prometheus.egg-info/requires.txt
pip_services3_prometheus.egg-info/top_level.txt
pip_services3_prometheus.egg-info/zip-safe
pip_services3_prometheus/build/DefaultPrometheusFactory.py
pip_services3_prometheus/build/__init__.py
pip_services3_prometheus/count/PrometheusCounterConverter.py
pip_services3_prometheus/count/PrometheusCounters.py
pip_services3_prometheus/count/__init__.py
pip_services3_prometheus/services/PrometheusMetricsService.py
pip_services3_prometheus/services/__init__.py
test/count/__init__.py
test/count/test_PrometheusCounterConverter.py
test/count/test_PrometheusCounters.py
test/fixtures/CountersFixture.py
test/fixtures/__init__.py
test/services/__init__.py
test/services/test_PrometheusMetricsService.py